bot/__init__.py
bot/actions.py
bot/base.py
bot/challenge_handler.py
bot/database.py
bot/direct_messaging.py
bot/instagram.py
bot/utils.py
config/__init__.py
config/settings.py
instaflow-0.1.0.dist-info/METADATA
instaflow-0.1.0.dist-info/WHEEL
instaflow-0.1.0.dist-info/entry_points.txt
instaflow-0.1.0.dist-info/top_level.txt
instaflow-0.1.0.dist-info/RECORD
