Metadata-Version: 2.4
Name: instaflow
Version: 0.1.0
Summary: A Python-based Instagram automation tool
Home-page: https://github.com/BimaPangestu28/InstaFlow
Author: Bima Pangestu
Author-email: bima@catalystlabs.id
Project-URL: Bug Tracker, https://github.com/BimaPangestu28/InstaFlow/issues
Project-URL: Website, https://instaflow.catalystlabs.id
Classifier: Programming Language :: Python :: 3
Classifier: Programming Language :: Python :: 3.8
Classifier: Programming Language :: Python :: 3.9
Classifier: Programming Language :: Python :: 3.10
Classifier: License :: OSI Approved :: MIT License
Classifier: Operating System :: OS Independent
Classifier: Development Status :: 3 - Alpha
Classifier: Intended Audience :: Developers
Classifier: Topic :: Software Development :: Libraries :: Python Modules
Requires-Python: >=3.8
Requires-Dist: selenium>=4.1.0
Requires-Dist: python-dotenv>=0.19.0
Dynamic: author
Dynamic: author-email
Dynamic: classifier
Dynamic: description
Dynamic: description-content-type
Dynamic: home-page
Dynamic: project-url
Dynamic: requires-dist
Dynamic: requires-python
Dynamic: summary
